LICENSE
MANIFEST.in
README.rst
setup.py
symbolator.py
nucanvas/__init__.py
nucanvas/cairo_backend.py
nucanvas/nucanvas.py
nucanvas/shapes.py
nucanvas/svg_backend.py
nucanvas/color/__init__.py
nucanvas/color/sinebow.py
symbolator.egg-info/PKG-INFO
symbolator.egg-info/SOURCES.txt
symbolator.egg-info/dependency_links.txt
symbolator.egg-info/entry_points.txt
symbolator.egg-info/requires.txt
symbolator.egg-info/top_level.txt
symbolator_sphinx/LICENSE.Sphinx
symbolator_sphinx/__init__.py
symbolator_sphinx/graphviz.py
symbolator_sphinx/symbolator_sphinx.py